datasette_template_sql/__init__.py
datasette_template_sql-1.0.2.dist-info/LICENSE
datasette_template_sql-1.0.2.dist-info/METADATA
datasette_template_sql-1.0.2.dist-info/WHEEL
datasette_template_sql-1.0.2.dist-info/entry_points.txt
datasette_template_sql-1.0.2.dist-info/top_level.txt
datasette_template_sql-1.0.2.dist-info/RECORD
