Metadata-Version: 2.1
Name: datasette-template-sql
Version: 1.0.2
Summary: Datasette plugin for executing SQL queries from templates
Home-page: https://github.com/simonw/datasette-template-sql
Author: Simon Willison
License: Apache License, Version 2.0
Project-URL: Issues, https://github.com/simonw/datasette-template-sql/issues
Project-URL: CI, https://github.com/simonw/datasette-template-sql/actions
Project-URL: Changelog, https://github.com/simonw/datasette-template-sql/releases
Platform: UNKNOWN
Requires-Python: >=3.6
Requires-Dist: datasette (>=0.54)
Provides-Extra: test
Requires-Dist: pytest ; extra == 'test'
Requires-Dist: pytest-asyncio ; extra == 'test'
Requires-Dist: sqlite-utils ; extra == 'test'
